santaim/__init__.py
santaim/__main__.py
santaim/core.py
santaim/enc.py
santaim/kill.py
santaim/lock.py
santaim/vrf.py
santaim-1.0.0.dist-info/licenses/LICENSE
santaim-1.0.0.dist-info/METADATA
santaim-1.0.0.dist-info/WHEEL
santaim-1.0.0.dist-info/top_level.txt
santaim-1.0.0.dist-info/RECORD
