Metadata-Version: 2.4
Name: santaim
Version: 1.0.0
Summary: Time-based expiration control system for Python applications
Author: mero
Author-email: mero <dev@santaim.com>
License: MIT
Keywords: time,expiration,control,license,protection
Classifier: Development Status :: 5 - Production/Stable
Classifier: Intended Audience :: Developers
Classifier: Topic :: Software Development :: Libraries :: Python Modules
Classifier: License :: OSI Approved :: MIT License
Classifier: Programming Language :: Python :: 3
Classifier: Programming Language :: Python :: 3.6
Classifier: Programming Language :: Python :: 3.7
Classifier: Programming Language :: Python :: 3.8
Classifier: Programming Language :: Python :: 3.9
Classifier: Programming Language :: Python :: 3.10
Classifier: Programming Language :: Python :: 3.11
Classifier: Programming Language :: Python :: 3.12
Classifier: Programming Language :: Python :: 3.13
Classifier: Operating System :: OS Independent
Requires-Python: >=3.6
License-File: LICENSE
Requires-Dist: requests>=2.20.0
Provides-Extra: full
Requires-Dist: psutil>=5.0.0; extra == "full"
Dynamic: author
Dynamic: license-file
Dynamic: requires-python
